<content type="application/x.deki0805+xml" title="href"><body xmlns:eval="http://mindtouch.com/2007/dekiscript">
<div class="noinclude"><span class="script">template.XULRefAttr()</span></div>
<dl><dt> <span class="script">template.XULAttr("href")</span> </dt><dd> Type: <em>string</em> </dd><dd> Defines a URL to open when this element is clicked. Requires the class attribute to include <a title="en/XUL/Style/text-link" href="/en/XUL/Style/text-link">text-link</a>. </dd></dl>
<div class="noinclude">
<pre class="eval">&lt;label href="<span class="nowiki">http://example.com</span>" class="text-link" value="Click here to go to example.com"/&gt;
</pre>
</div>
<div class="noinclude">
<p><span class="script"> wiki.languages( { "ja": "ja/XUL/Attribute/href", "pl": "pl/XUL/Atrybut/href" } ) </span></p>
</div></body></content>