<content type="application/x.deki0805+xml" title="allNotifications"><body xmlns:eval="http://mindtouch.com/2007/dekiscript">
<div class="noinclude"><span class="script">template.XULRefProp()</span></div>
<dl><dt> <span class="script">template.XULProp("allNotifications")</span> </dt><dd> Type: <em>nodeList</em> </dd><dd> NodeList of all notifications. This property is read-only. </dd></dl>
<div class="noinclude">
<p><span class="script"> wiki.languages( { "ja": "ja/XUL/Property/allNotifications" } ) </span></p>
</div></body></content>