<content type="application/x.deki0805+xml" title="tabbrowser"><body xmlns:eval="http://mindtouch.com/2007/dekiscript">
<div class="noinclude"><span class="script">template.XULRefElem()</span></div>
<p>This element is used for holding a set of read-only views of Web documents. It is similar to the <span class="script">template.XULElem("browser")</span> element, except that multiple documents can be displayed, each in a separate tab.</p>
<p><span class="script">template.Note("Starting in Firefox 3 (XULRunner/Gecko 1.9), this is only used in the main Firefox window and cannot be used in other XUL windows by third-party applications or extensions.")</span></p>
<dl> <dt>Attributes</dt> <dd><span class="script">template.PrefAnch("a-", "autocompleteenabled")</span>, <span class="script">template.PrefAnch("a-", "autocompletepopup")</span>, <span class="script">template.PrefAnch("a-", "autoscroll")</span>, <span class="script">template.PrefAnch("a-", "contentcontextmenu")</span>, <span class="script">template.PrefAnch("a-", "contenttooltip")</span>, <span class="script">template.PrefAnch("a-", "handleCtrlPageUpDown")</span>, <span class="script">template.PrefAnch("a-", "onbookmarkgroup")</span>, <span class="script">template.PrefAnch("a-", "onnewtab")</span>, <span class="script">PrefAnch("a-", "tabmodalPromptShowing")</span></dd>
</dl>
<dl> <dt>Properties</dt> <dd><span class="script">template.PrefAnch("p-", "browsers")</span>, <span class="script">template.PrefAnch("p-", "canGoBack")</span>, <span class="script">template.PrefAnch("p-", "canGoForward")</span>, <span class="script">template.PrefAnch("p-", "contentDocument")</span>, <span class="script">template.PrefAnch("p-", "contentTitle")</span>, <span class="script">template.PrefAnch("p-", "contentViewerEdit")</span>, <span class="script">template.PrefAnch("p-", "contentViewerFile")</span>, <span class="script">template.PrefAnch("p-", "contentWindow")</span>, <span class="script">template.PrefAnch("p-", "currentURI")</span>, <span class="script">template.PrefAnch("p-", "docShell")</span>, <span class="script">template.PrefAnch("p-", "documentCharsetInfo")</span>, <span class="script">template.PrefAnch("p-", "homePage")</span>, <span class="script">template.PrefAnch("p-", "markupDocumentViewer")</span>, <span class="script">template.PrefAnch("p-", "securityUI")</span>, <span class="script">template.PrefAnch("p-", "selectedBrowser")</span>, <span class="script">template.PrefAnch("p-", "selectedTab")</span>, <span class="script">template.PrefAnch("p-", "sessionHistory")</span>, <span class="script">template.PrefAnch("p-", "tabContainer")</span>, <span class="script">PrefAnch("p-", "tabs")</span>, <span class="script">PrefAnch("p-", "visibleTabs")</span>, <span class="script">template.PrefAnch("p-", "webBrowserFind")</span>, <span class="script">template.PrefAnch("p-", "webNavigation")</span>, <span class="script">template.PrefAnch("p-", "webProgress")</span></dd>
</dl>
<dl> <dt>Methods</dt> <dd><span class="script">template.PrefAnch("m-", "addProgressListener")</span>, <span class="script">template.PrefAnch("m-", "addTab")</span>, <span class="script">template.PrefAnch("m-", "addTabsProgressListener")</span>,<span class="script">template.PrefAnch("m-", "appendGroup")</span>, <span class="script">template.PrefAnch("m-", "getBrowserAtIndex")</span>, <span class="script">template.PrefAnch("m-", "getBrowserIndexForDocument")</span>, <span class="script">template.PrefAnch("m-", "getBrowserForDocument")</span>, <span class="script">template.PrefAnch("m-", "getBrowserForTab")</span>, <span class="script">PrefAnch("m-", "getIcon")</span>, <span class="script">template.PrefAnch("m-", "getNotificationBox")</span>, <span class="script">PrefAnch("m-", "getTabModalPromptBox")</span>, <span class="script">template.PrefAnch("m-", "goBack")</span>, <span class="script">template.PrefAnch("m-", "goBackGroup")</span>, <span class="script">template.PrefAnch("m-", "goForward")</span>, <span class="script">template.PrefAnch("m-", "goForwardGroup")</span>, <span class="script">template.PrefAnch("m-", "goHome")</span>, <span class="script">template.PrefAnch("m-", "gotoIndex")</span>, <span class="script">template.PrefAnch("m-", "loadGroup")</span>, <span class="script">template.PrefAnch("m-", "loadOneTab")</span>, <span class="script">template.PrefAnch("m-", "loadTabs")</span>, <span class="script">template.PrefAnch("m-", "loadURI")</span>, <span class="script">template.PrefAnch("m-", "loadURIWithFlags")</span>, <span class="script">template.PrefAnch("m-", "moveTabTo")</span>, <span class="script">PrefAnch("m-", "pinTab")</span>, <span class="script">template.PrefAnch("m-", "reload")</span>, <span class="script">template.PrefAnch("m-", "reloadAllTabs")</span>, <span class="script">template.PrefAnch("m-", "reloadTab")</span>, <span class="script">template.PrefAnch("m-", "reloadWithFlags")</span>, <span class="script">template.PrefAnch("m-", "removeAllTabsBut")</span>, <span class="script">template.PrefAnch("m-", "removeCurrentTab")</span>, <span class="script">template.PrefAnch("m-", "removeProgressListener")</span>, <span class="script">template.PrefAnch("m-", "removeTab")</span>, <span class="script">template.PrefAnch("m-", "removeTabsProgressListener")</span>,<span class="script">template.PrefAnch("m-", "replaceGroup")</span>, <span class="script">template.PrefAnch("m-", "selectTabAtIndex")</span>, <span class="script">PrefAnch("m-", "setIcon")</span>, <span class="script">PrefAnch("m-", "showOnlyTheseTabs")</span>, <span class="script">template.PrefAnch("m-", "stop")</span>, <span class="script">PrefAnch("m-", "unpinTab")</span></dd>
</dl>
<h3 name="Attributes">Attributes</h3>
<p><span class="script">template.XULAttrInherited()</span> <span class="script">template.XULAttrInc("autocompleteenabled")</span> <span class="script">template.XULAttrInc("autocompletepopup")</span> <span class="script">template.XULAttrInc("autoscroll")</span> <span class="script">template.XULAttrInc("contentcontextmenu")</span> <span class="script">template.XULAttrInc("contenttooltip")</span> <span class="script">template.XULAttrInc("handleCtrlPageUpDown")</span> <span class="script">template.XULAttrInc("onbookmarkgroup")</span> <span class="script">template.XULAttrInc("onnewtab")</span> <span class="script">XULAttrInc("tabmodalPromptShowing")</span></p>
<h3 name="Properties">Properties</h3>
<p><span class="script">template.XULPropInherited()</span> <span class="script">template.XULPropInc("browsers")</span> <span class="script">template.XULPropInc("canGoBack")</span> <span class="script">template.XULPropInc("canGoForward")</span> <span class="script">template.XULPropInc("contentDocument")</span> <span class="script">template.XULPropInc("contentTitle")</span> <span class="script">template.XULPropInc("contentViewerEdit")</span> <span class="script">template.XULPropInc("contentViewerFile")</span> <span class="script">template.XULPropInc("contentWindow")</span> <span class="script">template.XULPropInc("currentURI")</span> <span class="script">template.XULPropInc("docShell")</span> <span class="script">template.XULPropInc("documentCharsetInfo")</span> <span class="script">template.XULPropInc("homePage")</span> <span class="script">template.XULPropInc("markupDocumentViewer")</span> <span class="script">template.XULPropInc("securityUI")</span> <span class="script">template.XULPropInc("selectedBrowser")</span> <span class="script">template.XULPropInc("selectedTab")</span> <span class="script">template.XULPropInc("sessionHistory")</span> <span class="script">template.XULPropInc("tabContainer")</span> <span class="script">XULPropInc("tabbrowser.tabs")</span> <span class="script">XULPropInc("visibleTabs")</span> <span class="script">template.XULPropInc("webBrowserFind")</span> <span class="script">template.XULPropInc("webNavigation")</span> <span class="script">template.XULPropInc("webProgress")</span></p>
<h3 name="Methods">Methods</h3>
<p><span class="script">template.XULMethInherited()</span> <span class="script">template.XULMethInc("addProgressListener")</span> <span class="script">template.XULMethInc("addTab")</span> <span class="script">template.XULMethInc("addTabsProgressListener")</span> <span class="script">template.XULMethInc("appendGroup")</span> <span class="script">template.XULMethInc("getBrowserAtIndex")</span> <span class="script">template.XULMethInc("getBrowserIndexForDocument")</span> <span class="script">template.XULMethInc("getBrowserForDocument")</span> <span class="script">template.XULMethInc("getBrowserForTab")</span> <span class="script">XULMethInc("getIcon")</span> <span class="script">template.XULMethInc("getNotificationBox")</span> <span class="script">XULMethInc("getTabModalPromptBox")</span> <span class="script">template.XULMethInc("goBack")</span> <span class="script">template.XULMethInc("goBackGroup")</span> <span class="script">template.XULMethInc("goForward")</span> <span class="script">template.XULMethInc("goForwardGroup")</span> <span class="script">template.XULMethInc("goHome")</span> <span class="script">template.XULMethInc("gotoIndex")</span> <span class="script">template.XULMethInc("loadGroup")</span> <span class="script">template.XULMethInc("loadOneTab")</span> <span class="script">template.XULMethInc("loadTabs")</span> <span class="script">template.XULMethInc("loadURI")</span> <span class="script">template.XULMethInc("loadURIWithFlags")</span> <span class="script">template.XULMethInc("moveTabTo")</span> <span class="script">XULMethInc("pinTab")</span> <span class="script">template.XULMethInc("reload")</span> <span class="script">template.XULMethInc("reloadAllTabs")</span> <span class="script">template.XULMethInc("reloadTab")</span> <span class="script">template.XULMethInc("reloadWithFlags")</span> <span class="script">template.XULMethInc("removeAllTabsBut")</span> <span class="script">template.XULMethInc("removeCurrentTab")</span> <span class="script">template.XULMethInc("removeProgressListener")</span> <span class="script">template.XULMethInc("removeTab")</span> <span class="script">template.XULMethInc("removeTabsProgressListener")</span> <span class="script">template.XULMethInc("replaceGroup")</span> <span class="script">template.XULMethInc("selectTabAtIndex")</span> <span class="script">XULMethInc("setIcon")</span> <span class="script">XULMethInc("showOnlyTheseTabs")</span> <span class="script">template.XULMethInc("stop")</span> <span class="script">XULMethInc("unpinTab")</span></p>
<h3 name="Related">Related</h3>
<ul> <li><a title="en/Code_snippets/Tabbed_browser" href="/en/Code_snippets/Tabbed_browser">Code snippets:Tabbed browser</a></li>
</ul>
<p><span class="script"> wiki.languages( { "ja": "ja/XUL/tabbrowser", "pl": "pl/XUL/tabbrowser" } ) </span></p></body></content>